inputscriptparser/__init__.py
inputscriptparser/common.py
inputscriptparser/interpreters.py
inputscriptparser/parsers/__init__.py
inputscriptparser/parsers/inputscript.py
inputscriptparser/parsers/labeledscript.py
inputscriptparser/show_script.py
inputscriptparser-1.2.1.dist-info/LICENSE.txt
inputscriptparser-1.2.1.dist-info/METADATA
inputscriptparser-1.2.1.dist-info/WHEEL
inputscriptparser-1.2.1.dist-info/entry_points.txt
inputscriptparser-1.2.1.dist-info/RECORD
