Metadata-Version: 2.3
Name: inputscriptparser
Version: 1.2.1
Summary: A parser for script-style input data.
License: MIT
Author: takatoh
Author-email: takatoh.m@gmail.com
Requires-Python: >=3.9,<4.0
Classifier: License :: OSI Approved :: MIT License
Classifier: Programming Language :: Python :: 3
Classifier: Programming Language :: Python :: 3.9
Classifier: Programming Language :: Python :: 3.10
Classifier: Programming Language :: Python :: 3.11
Classifier: Programming Language :: Python :: 3.12
Classifier: Programming Language :: Python :: 3.13
Requires-Dist: lark (>=1.1.0,<2.0.0)
Project-URL: Homepage, https://github.com/takatoh/inputscriptparser
Project-URL: Repository, https://github.com/takatoh/inputscriptparser
